<?xml version="1.0" encoding="utf-8"?>
<clothing-items>
 <clothing>
  <id>
   317026289
  </id>
  <name>
   Vans Handbags I-1915
  </name>
  <category>
   Handbags
  </category>
  <size>
   M
  </size>
  <color>
   Оранжевый
  </color>
  <material>
   Шелк
  </material>
  <price>
   234866
  </price>
  <rating>
   3.45
  </rating>
  <reviews>
   841498
  </reviews>
  <new>
   -
  </new>
  <exclusive>
   yes
  </exclusive>
 </clothing>
 <clothing>
  <id>
   764883174
  </id>
  <name>
   Under Armour Gloves C-3991
  </name>
  <category>
   Gloves
  </category>
  <size>
   XXL
  </size>
  <color>
   Оранжевый
  </color>
  <material>
   Вискоза
  </material>
  <price>
   931453
  </price>
  <rating>
   3.23
  </rating>
  <reviews>
   1868
  </reviews>
  <exclusive>
   yes
  </exclusive>
  <sporty>
   no
  </sporty>
 </clothing>
 <clothing>
  <id>
   491055358
  </id>
  <name>
   DC Umbrellas A-2364
  </name>
  <category>
   Umbrellas
  </category>
  <size>
   XXL
  </size>
  <color>
   Голубой
  </color>
  <material>
   Хлопок
  </material>
  <price>
   925215
  </price>
  <rating>
   1.78
  </rating>
  <reviews>
   250496
  </reviews>
  <new>
   -
  </new>
  <exclusive>
   no
  </exclusive>
  <sporty>
   yes
  </sporty>
 </clothing>
 <clothing>
  <id>
   367389980
  </id>
  <name>
   Converse Belts C-8336
  </name>
  <category>
   Belts
  </category>
  <size>
   M
  </size>
  <color>
   Фиолетовый
  </color>
  <material>
   Полиэстер
  </material>
  <price>
   880322
  </price>
  <rating>
   1.99
  </rating>
  <reviews>
   370584
  </reviews>
  <new>
   -
  </new>
  <exclusive>
   no
  </exclusive>
 </clothing>
 <clothing>
  <id>
   219316496
  </id>
  <name>
   Brooks Skirt Y-2421
  </name>
  <category>
   Skirt
  </category>
  <size>
   L
  </size>
  <color>
   Оранжевый
  </color>
  <material>
   Лен
  </material>
  <price>
   570137
  </price>
  <rating>
   1.04
  </rating>
  <reviews>
   941974
  </reviews>
  <new>
   -
  </new>
  <sporty>
   yes
  </sporty>
 </clothing>
 <clothing>
  <id>
   169834440
  </id>
  <name>
   Puma Skirt G-5365
  </name>
  <category>
   Skirt
  </category>
  <size>
   S
  </size>
  <color>
   Зеленый
  </color>
  <material>
   Кожа
  </material>
  <price>
   317948
  </price>
  <rating>
   3.43
  </rating>
  <reviews>
   685422
  </reviews>
  <exclusive>
   yes
  </exclusive>
  <sporty>
   no
  </sporty>
 </clothing>
 <clothing>
  <id>
   264649328
  </id>
  <name>
   PleinSport Blouse M-2187
  </name>
  <category>
   Blouse
  </category>
  <size>
   XXL
  </size>
  <color>
   Красный
  </color>
  <material>
   Шерсть
  </material>
  <price>
   266961
  </price>
  <rating>
   2.67
  </rating>
  <reviews>
   76647
  </reviews>
  <new>
   -
  </new>
  <exclusive>
   no
  </exclusive>
 </clothing>
 <clothing>
  <id>
   100258984
  </id>
  <name>
   Lacoste Umbrellas G-6385
  </name>
  <category>
   Umbrellas
  </category>
  <size>
   M
  </size>
  <color>
   Желтый
  </color>
  <material>
   Шерсть
  </material>
  <price>
   149978
  </price>
  <rating>
   4.08
  </rating>
  <reviews>
   731810
  </reviews>
  <new>
   +
  </new>
 </clothing>
 <clothing>
  <id>
   300894673
  </id>
  <name>
   Nike Umbrellas K-2852
  </name>
  <category>
   Umbrellas
  </category>
  <size>
   M
  </size>
  <color>
   Голубой
  </color>
  <material>
   Полиэстер
  </material>
  <price>
   923196
  </price>
  <rating>
   4.38
  </rating>
  <reviews>
   831837
  </reviews>
  <new>
   -
  </new>
  <exclusive>
   yes
  </exclusive>
  <sporty>
   no
  </sporty>
 </clothing>
 <clothing>
  <id>
   231277990
  </id>
  <name>
   New Balance Jacket L-8117
  </name>
  <category>
   Jacket
  </category>
  <size>
   M
  </size>
  <color>
   Голубой
  </color>
  <material>
   Хлопок
  </material>
  <price>
   519812
  </price>
  <rating>
   1.28
  </rating>
  <reviews>
   720918
  </reviews>
  <new>
   +
  </new>
  <sporty>
   yes
  </sporty>
 </clothing>
 <clothing>
  <id>
   893256737
  </id>
  <name>
   PleinSport Hat D-7321
  </name>
  <category>
   Hat
  </category>
  <size>
   M
  </size>
  <color>
   Красный
  </color>
  <material>
   Полиэстер
  </material>
  <price>
   134916
  </price>
  <rating>
   1.16
  </rating>
  <reviews>
   799069
  </reviews>
  <exclusive>
   no
  </exclusive>
  <sporty>
   no
  </sporty>
 </clothing>
 <clothing>
  <id>
   806741355
  </id>
  <name>
   Asics Gloves Y-7265
  </name>
  <category>
   Gloves
  </category>
  <size>
   L
  </size>
  <color>
   Красный
  </color>
  <material>
   Нейлон
  </material>
  <price>
   484427
  </price>
  <rating>
   3.12
  </rating>
  <reviews>
   261249
  </reviews>
  <exclusive>
   yes
  </exclusive>
 </clothing>
 <clothing>
  <id>
   590387555
  </id>
  <name>
   Puma Dress M-7204
  </name>
  <category>
   Dress
  </category>
  <size>
   XXL
  </size>
  <color>
   Красный
  </color>
  <material>
   Полиэстер
  </material>
  <price>
   987432
  </price>
  <rating>
   2.89
  </rating>
  <reviews>
   836213
  </reviews>
  <exclusive>
   yes
  </exclusive>
 </clothing>
 <clothing>
  <id>
   981509218
  </id>
  <name>
   Converse T-shirt C-5900
  </name>
  <category>
   T-shirt
  </category>
  <size>
   S
  </size>
  <color>
   Оранжевый
  </color>
  <material>
   Лен
  </material>
  <price>
   784327
  </price>
  <rating>
   2.45
  </rating>
  <reviews>
   234619
  </reviews>
  <new>
   -
  </new>
  <exclusive>
   yes
  </exclusive>
  <sporty>
   yes
  </sporty>
 </clothing>
 <clothing>
  <id>
   691962690
  </id>
  <name>
   Lacoste Shirt Q-1809
  </name>
  <category>
   Shirt
  </category>
  <size>
   XXL
  </size>
  <color>
   Синий
  </color>
  <material>
   Полиэстер
  </material>
  <price>
   185513
  </price>
  <rating>
   1.75
  </rating>
  <reviews>
   611107
  </reviews>
  <exclusive>
   yes
  </exclusive>
  <sporty>
   no
  </sporty>
 </clothing>
 <clothing>
  <id>
   103508166
  </id>
  <name>
   Fila Handbags Q-8265
  </name>
  <category>
   Handbags
  </category>
  <size>
   XL
  </size>
  <color>
   Оранжевый
  </color>
  <material>
   Вискоза
  </material>
  <price>
   440542
  </price>
  <rating>
   3.81
  </rating>
  <reviews>
   263284
  </reviews>
  <sporty>
   yes
  </sporty>
 </clothing>
 <clothing>
  <id>
   943860357
  </id>
  <name>
   Puma Jeans S-9936
  </name>
  <category>
   Jeans
  </category>
  <size>
   XL
  </size>
  <color>
   Оранжевый
  </color>
  <material>
   Вискоза
  </material>
  <price>
   922898
  </price>
  <rating>
   2.42
  </rating>
  <reviews>
   479765
  </reviews>
  <exclusive>
   yes
  </exclusive>
  <sporty>
   yes
  </sporty>
 </clothing>
 <clothing>
  <id>
   585866153
  </id>
  <name>
   Converse Shoes Q-4045
  </name>
  <category>
   Shoes
  </category>
  <size>
   M
  </size>
  <color>
   Синий
  </color>
  <material>
   Шерсть
  </material>
  <price>
   710563
  </price>
  <rating>
   1.09
  </rating>
  <reviews>
   959589
  </reviews>
  <exclusive>
   yes
  </exclusive>
  <sporty>
   yes
  </sporty>
 </clothing>
 <clothing>
  <id>
   874353122
  </id>
  <name>
   DC Hat I-5212
  </name>
  <category>
   Hat
  </category>
  <size>
   XXL
  </size>
  <color>
   Оранжевый
  </color>
  <material>
   Шелк
  </material>
  <price>
   714636
  </price>
  <rating>
   2.58
  </rating>
  <reviews>
   713432
  </reviews>
  <new>
   -
  </new>
  <exclusive>
   yes
  </exclusive>
  <sporty>
   no
  </sporty>
 </clothing>
 <clothing>
  <id>
   479534352
  </id>
  <name>
   Asics Belts R-6241
  </name>
  <category>
   Belts
  </category>
  <size>
   L
  </size>
  <color>
   Голубой
  </color>
  <material>
   Шелк
  </material>
  <price>
   738820
  </price>
  <rating>
   4.64
  </rating>
  <reviews>
   44669
  </reviews>
  <new>
   +
  </new>
 </clothing>
 <clothing>
  <id>
   339765742
  </id>
  <name>
   Puma Socks Q-4359
  </name>
  <category>
   Socks
  </category>
  <size>
   XXL
  </size>
  <color>
   Красный
  </color>
  <material>
   Полиэстер
  </material>
  <price>
   178869
  </price>
  <rating>
   3.57
  </rating>
  <reviews>
   399004
  </reviews>
  <new>
   +
  </new>
  <exclusive>
   no
  </exclusive>
  <sporty>
   no
  </sporty>
 </clothing>
 <clothing>
  <id>
   365870216
  </id>
  <name>
   Ellesse Belts M-5528
  </name>
  <category>
   Belts
  </category>
  <size>
   XL
  </size>
  <color>
   Зеленый
  </color>
  <material>
   Хлопок
  </material>
  <price>
   844928
  </price>
  <rating>
   3.27
  </rating>
  <reviews>
   830480
  </reviews>
  <new>
   -
  </new>
  <exclusive>
   no
  </exclusive>
 </clothing>
 <clothing>
  <id>
   126826190
  </id>
  <name>
   Adidas Blouse B-6341
  </name>
  <category>
   Blouse
  </category>
  <size>
   XXL
  </size>
  <color>
   Оранжевый
  </color>
  <material>
   Кожа
  </material>
  <price>
   442021
  </price>
  <rating>
   1.56
  </rating>
  <reviews>
   791644
  </reviews>
  <new>
   -
  </new>
 </clothing>
 <clothing>
  <id>
   116333977
  </id>
  <name>
   DC T-shirt M-6680
  </name>
  <category>
   T-shirt
  </category>
  <size>
   XL
  </size>
  <color>
   Зеленый
  </color>
  <material>
   Шелк
  </material>
  <price>
   512902
  </price>
  <rating>
   1.48
  </rating>
  <reviews>
   266685
  </reviews>
  <new>
   +
  </new>
  <exclusive>
   no
  </exclusive>
 </clothing>
 <clothing>
  <id>
   809831265
  </id>
  <name>
   Ellesse Jeans I-3084
  </name>
  <category>
   Jeans
  </category>
  <size>
   L
  </size>
  <color>
   Голубой
  </color>
  <material>
   Кожа
  </material>
  <price>
   947376
  </price>
  <rating>
   3.82
  </rating>
  <reviews>
   515240
  </reviews>
  <new>
   +
  </new>
 </clothing>
 <clothing>
  <id>
   535724127
  </id>
  <name>
   Brooks Gloves M-6170
  </name>
  <category>
   Gloves
  </category>
  <size>
   L
  </size>
  <color>
   Желтый
  </color>
  <material>
   Нейлон
  </material>
  <price>
   648870
  </price>
  <rating>
   2.02
  </rating>
  <reviews>
   568474
  </reviews>
  <new>
   -
  </new>
  <exclusive>
   yes
  </exclusive>
 </clothing>
 <clothing>
  <id>
   202567489
  </id>
  <name>
   Converse Blouse D-6990
  </name>
  <category>
   Blouse
  </category>
  <size>
   L
  </size>
  <color>
   Оранжевый
  </color>
  <material>
   Кожа
  </material>
  <price>
   629092
  </price>
  <rating>
   4.44
  </rating>
  <reviews>
   543789
  </reviews>
  <sporty>
   no
  </sporty>
 </clothing>
 <clothing>
  <id>
   608426963
  </id>
  <name>
   Nike Shirt A-3292
  </name>
  <category>
   Shirt
  </category>
  <size>
   S
  </size>
  <color>
   Голубой
  </color>
  <material>
   Нейлон
  </material>
  <price>
   936918
  </price>
  <rating>
   1.98
  </rating>
  <reviews>
   719943
  </reviews>
  <exclusive>
   yes
  </exclusive>
 </clothing>
 <clothing>
  <id>
   137264006
  </id>
  <name>
   Addidas Skirt Q-9557
  </name>
  <category>
   Skirt
  </category>
  <size>
   S
  </size>
  <color>
   Голубой
  </color>
  <material>
   Шелк
  </material>
  <price>
   869863
  </price>
  <rating>
   2.42
  </rating>
  <reviews>
   36372
  </reviews>
  <exclusive>
   no
  </exclusive>
  <sporty>
   yes
  </sporty>
 </clothing>
 <clothing>
  <id>
   221300031
  </id>
  <name>
   Nike Gloves C-1737
  </name>
  <category>
   Gloves
  </category>
  <size>
   XXL
  </size>
  <color>
   Зеленый
  </color>
  <material>
   Хлопок
  </material>
  <price>
   854899
  </price>
  <rating>
   4.31
  </rating>
  <reviews>
   229635
  </reviews>
  <exclusive>
   no
  </exclusive>
  <sporty>
   no
  </sporty>
 </clothing>
 <clothing>
  <id>
   647113437
  </id>
  <name>
   Nike Gloves M-6482
  </name>
  <category>
   Gloves
  </category>
  <size>
   XXL
  </size>
  <color>
   Голубой
  </color>
  <material>
   Лен
  </material>
  <price>
   811828
  </price>
  <rating>
   4.54
  </rating>
  <reviews>
   989167
  </reviews>
  <new>
   +
  </new>
  <exclusive>
   no
  </exclusive>
  <sporty>
   yes
  </sporty>
 </clothing>
 <clothing>
  <id>
   314095460
  </id>
  <name>
   Adidas Jacket P-6688
  </name>
  <category>
   Jacket
  </category>
  <size>
   S
  </size>
  <color>
   Фиолетовый
  </color>
  <material>
   Лен
  </material>
  <price>
   958379
  </price>
  <rating>
   4.85
  </rating>
  <reviews>
   640435
  </reviews>
  <exclusive>
   no
  </exclusive>
  <sporty>
   yes
  </sporty>
 </clothing>
 <clothing>
  <id>
   154262269
  </id>
  <name>
   Addidas Jacket K-1182
  </name>
  <category>
   Jacket
  </category>
  <size>
   S
  </size>
  <color>
   Красный
  </color>
  <material>
   Хлопок
  </material>
  <price>
   585739
  </price>
  <rating>
   1.51
  </rating>
  <reviews>
   7375
  </reviews>
  <exclusive>
   no
  </exclusive>
  <sporty>
   yes
  </sporty>
 </clothing>
 <clothing>
  <id>
   598661260
  </id>
  <name>
   DC T-shirt J-7539
  </name>
  <category>
   T-shirt
  </category>
  <size>
   S
  </size>
  <color>
   Синий
  </color>
  <material>
   Полиэстер
  </material>
  <price>
   936557
  </price>
  <rating>
   3.53
  </rating>
  <reviews>
   73390
  </reviews>
  <new>
   -
  </new>
  <exclusive>
   no
  </exclusive>
  <sporty>
   yes
  </sporty>
 </clothing>
</clothing-items>
