<?xml version="1.0" encoding="utf-8"?>
<clothing-items>
 <clothing>
  <id>
   955138628
  </id>
  <name>
   PleinSport Jacket B-6026
  </name>
  <category>
   Jacket
  </category>
  <size>
   S
  </size>
  <color>
   Синий
  </color>
  <material>
   Хлопок
  </material>
  <price>
   619665
  </price>
  <rating>
   3.03
  </rating>
  <reviews>
   781955
  </reviews>
  <new>
   +
  </new>
 </clothing>
 <clothing>
  <id>
   744960235
  </id>
  <name>
   Nike Socks F-7600
  </name>
  <category>
   Socks
  </category>
  <size>
   XL
  </size>
  <color>
   Синий
  </color>
  <material>
   Шерсть
  </material>
  <price>
   136758
  </price>
  <rating>
   1.67
  </rating>
  <reviews>
   72614
  </reviews>
 </clothing>
 <clothing>
  <id>
   211629613
  </id>
  <name>
   Puma Hat M-3374
  </name>
  <category>
   Hat
  </category>
  <size>
   XL
  </size>
  <color>
   Красный
  </color>
  <material>
   Шерсть
  </material>
  <price>
   841242
  </price>
  <rating>
   4.0
  </rating>
  <reviews>
   229490
  </reviews>
  <new>
   -
  </new>
  <exclusive>
   no
  </exclusive>
  <sporty>
   yes
  </sporty>
 </clothing>
 <clothing>
  <id>
   473182885
  </id>
  <name>
   Ellesse Handbags Z-3295
  </name>
  <category>
   Handbags
  </category>
  <size>
   L
  </size>
  <color>
   Зеленый
  </color>
  <material>
   Вискоза
  </material>
  <price>
   591565
  </price>
  <rating>
   3.04
  </rating>
  <reviews>
   452286
  </reviews>
  <exclusive>
   yes
  </exclusive>
 </clothing>
 <clothing>
  <id>
   262482830
  </id>
  <name>
   Addidas Jeans C-1774
  </name>
  <category>
   Jeans
  </category>
  <size>
   S
  </size>
  <color>
   Зеленый
  </color>
  <material>
   Полиэстер
  </material>
  <price>
   501992
  </price>
  <rating>
   2.62
  </rating>
  <reviews>
   576650
  </reviews>
  <exclusive>
   yes
  </exclusive>
 </clothing>
 <clothing>
  <id>
   735922467
  </id>
  <name>
   Vans Skirt W-1313
  </name>
  <category>
   Skirt
  </category>
  <size>
   XXL
  </size>
  <color>
   Синий
  </color>
  <material>
   Нейлон
  </material>
  <price>
   464873
  </price>
  <rating>
   1.49
  </rating>
  <reviews>
   932493
  </reviews>
  <new>
   -
  </new>
  <exclusive>
   yes
  </exclusive>
  <sporty>
   yes
  </sporty>
 </clothing>
 <clothing>
  <id>
   149675622
  </id>
  <name>
   Reebok Sweater Q-1942
  </name>
  <category>
   Sweater
  </category>
  <size>
   XXL
  </size>
  <color>
   Зеленый
  </color>
  <material>
   Полиэстер
  </material>
  <price>
   779733
  </price>
  <rating>
   4.46
  </rating>
  <reviews>
   603633
  </reviews>
  <new>
   -
  </new>
  <exclusive>
   no
  </exclusive>
 </clothing>
 <clothing>
  <id>
   693513048
  </id>
  <name>
   Addidas Belts D-4153
  </name>
  <category>
   Belts
  </category>
  <size>
   L
  </size>
  <color>
   Оранжевый
  </color>
  <material>
   Кожа
  </material>
  <price>
   942298
  </price>
  <rating>
   4.61
  </rating>
  <reviews>
   429827
  </reviews>
  <new>
   -
  </new>
  <exclusive>
   yes
  </exclusive>
  <sporty>
   no
  </sporty>
 </clothing>
 <clothing>
  <id>
   336567500
  </id>
  <name>
   Vans Shirt J-4630
  </name>
  <category>
   Shirt
  </category>
  <size>
   M
  </size>
  <color>
   Желтый
  </color>
  <material>
   Полиэстер
  </material>
  <price>
   248799
  </price>
  <rating>
   4.76
  </rating>
  <reviews>
   625881
  </reviews>
  <new>
   -
  </new>
  <exclusive>
   yes
  </exclusive>
  <sporty>
   yes
  </sporty>
 </clothing>
 <clothing>
  <id>
   430006686
  </id>
  <name>
   New Balance Belts Q-9464
  </name>
  <category>
   Belts
  </category>
  <size>
   XL
  </size>
  <color>
   Зеленый
  </color>
  <material>
   Полиэстер
  </material>
  <price>
   947112
  </price>
  <rating>
   3.43
  </rating>
  <reviews>
   49345
  </reviews>
  <new>
   +
  </new>
  <exclusive>
   no
  </exclusive>
 </clothing>
 <clothing>
  <id>
   353899618
  </id>
  <name>
   Brooks Dress H-5106
  </name>
  <category>
   Dress
  </category>
  <size>
   M
  </size>
  <color>
   Желтый
  </color>
  <material>
   Лен
  </material>
  <price>
   204681
  </price>
  <rating>
   1.92
  </rating>
  <reviews>
   833076
  </reviews>
  <new>
   -
  </new>
  <exclusive>
   no
  </exclusive>
 </clothing>
 <clothing>
  <id>
   506706465
  </id>
  <name>
   Converse Socks Z-1859
  </name>
  <category>
   Socks
  </category>
  <size>
   XL
  </size>
  <color>
   Оранжевый
  </color>
  <material>
   Лен
  </material>
  <price>
   701654
  </price>
  <rating>
   1.42
  </rating>
  <reviews>
   159489
  </reviews>
  <exclusive>
   no
  </exclusive>
  <sporty>
   no
  </sporty>
 </clothing>
 <clothing>
  <id>
   548432211
  </id>
  <name>
   Converse Socks J-8620
  </name>
  <category>
   Socks
  </category>
  <size>
   L
  </size>
  <color>
   Красный
  </color>
  <material>
   Кожа
  </material>
  <price>
   671948
  </price>
  <rating>
   3.88
  </rating>
  <reviews>
   843498
  </reviews>
  <new>
   -
  </new>
  <sporty>
   no
  </sporty>
 </clothing>
 <clothing>
  <id>
   333432141
  </id>
  <name>
   Brooks Jeans L-2401
  </name>
  <category>
   Jeans
  </category>
  <size>
   XXL
  </size>
  <color>
   Желтый
  </color>
  <material>
   Шелк
  </material>
  <price>
   440681
  </price>
  <rating>
   3.21
  </rating>
  <reviews>
   588057
  </reviews>
  <sporty>
   yes
  </sporty>
 </clothing>
 <clothing>
  <id>
   322287003
  </id>
  <name>
   Fila Handbags U-9242
  </name>
  <category>
   Handbags
  </category>
  <size>
   XL
  </size>
  <color>
   Фиолетовый
  </color>
  <material>
   Хлопок
  </material>
  <price>
   239022
  </price>
  <rating>
   3.27
  </rating>
  <reviews>
   768617
  </reviews>
  <new>
   +
  </new>
 </clothing>
 <clothing>
  <id>
   803333075
  </id>
  <name>
   Ellesse Blouse G-1210
  </name>
  <category>
   Blouse
  </category>
  <size>
   L
  </size>
  <color>
   Голубой
  </color>
  <material>
   Нейлон
  </material>
  <price>
   808120
  </price>
  <rating>
   3.88
  </rating>
  <reviews>
   511786
  </reviews>
  <new>
   -
  </new>
  <exclusive>
   no
  </exclusive>
 </clothing>
 <clothing>
  <id>
   901579049
  </id>
  <name>
   Ellesse Umbrellas R-1594
  </name>
  <category>
   Umbrellas
  </category>
  <size>
   S
  </size>
  <color>
   Красный
  </color>
  <material>
   Шерсть
  </material>
  <price>
   514014
  </price>
  <rating>
   2.83
  </rating>
  <reviews>
   27846
  </reviews>
  <exclusive>
   no
  </exclusive>
  <sporty>
   yes
  </sporty>
 </clothing>
 <clothing>
  <id>
   393645890
  </id>
  <name>
   Addidas Jeans E-8255
  </name>
  <category>
   Jeans
  </category>
  <size>
   M
  </size>
  <color>
   Синий
  </color>
  <material>
   Шерсть
  </material>
  <price>
   782846
  </price>
  <rating>
   1.42
  </rating>
  <reviews>
   246853
  </reviews>
  <exclusive>
   yes
  </exclusive>
 </clothing>
 <clothing>
  <id>
   523018364
  </id>
  <name>
   Adidas T-shirt K-6743
  </name>
  <category>
   T-shirt
  </category>
  <size>
   XXL
  </size>
  <color>
   Зеленый
  </color>
  <material>
   Кожа
  </material>
  <price>
   109789
  </price>
  <rating>
   3.65
  </rating>
  <reviews>
   455043
  </reviews>
  <exclusive>
   yes
  </exclusive>
 </clothing>
 <clothing>
  <id>
   956798849
  </id>
  <name>
   Under Armour Sweater I-8777
  </name>
  <category>
   Sweater
  </category>
  <size>
   XXL
  </size>
  <color>
   Синий
  </color>
  <material>
   Нейлон
  </material>
  <price>
   761789
  </price>
  <rating>
   3.07
  </rating>
  <reviews>
   687000
  </reviews>
  <new>
   -
  </new>
  <exclusive>
   yes
  </exclusive>
  <sporty>
   no
  </sporty>
 </clothing>
 <clothing>
  <id>
   932690444
  </id>
  <name>
   Asics Pants J-4244
  </name>
  <category>
   Pants
  </category>
  <size>
   XXL
  </size>
  <color>
   Голубой
  </color>
  <material>
   Лен
  </material>
  <price>
   947567
  </price>
  <rating>
   2.13
  </rating>
  <reviews>
   170631
  </reviews>
  <exclusive>
   yes
  </exclusive>
  <sporty>
   yes
  </sporty>
 </clothing>
 <clothing>
  <id>
   426374417
  </id>
  <name>
   Puma Pants Y-3810
  </name>
  <category>
   Pants
  </category>
  <size>
   S
  </size>
  <color>
   Желтый
  </color>
  <material>
   Нейлон
  </material>
  <price>
   881485
  </price>
  <rating>
   1.65
  </rating>
  <reviews>
   417465
  </reviews>
  <exclusive>
   yes
  </exclusive>
  <sporty>
   no
  </sporty>
 </clothing>
 <clothing>
  <id>
   723060801
  </id>
  <name>
   Reebok Pants V-9155
  </name>
  <category>
   Pants
  </category>
  <size>
   L
  </size>
  <color>
   Зеленый
  </color>
  <material>
   Хлопок
  </material>
  <price>
   877411
  </price>
  <rating>
   1.26
  </rating>
  <reviews>
   992671
  </reviews>
  <new>
   -
  </new>
  <sporty>
   no
  </sporty>
 </clothing>
 <clothing>
  <id>
   330950058
  </id>
  <name>
   Addidas Blouse K-7081
  </name>
  <category>
   Blouse
  </category>
  <size>
   M
  </size>
  <color>
   Голубой
  </color>
  <material>
   Нейлон
  </material>
  <price>
   463682
  </price>
  <rating>
   4.68
  </rating>
  <reviews>
   640465
  </reviews>
  <new>
   +
  </new>
  <exclusive>
   no
  </exclusive>
 </clothing>
 <clothing>
  <id>
   292521467
  </id>
  <name>
   Reebok Shirt H-4879
  </name>
  <category>
   Shirt
  </category>
  <size>
   M
  </size>
  <color>
   Голубой
  </color>
  <material>
   Вискоза
  </material>
  <price>
   741702
  </price>
  <rating>
   2.58
  </rating>
  <reviews>
   106736
  </reviews>
  <new>
   +
  </new>
  <sporty>
   yes
  </sporty>
 </clothing>
 <clothing>
  <id>
   747149889
  </id>
  <name>
   Converse Belts I-4779
  </name>
  <category>
   Belts
  </category>
  <size>
   XL
  </size>
  <color>
   Синий
  </color>
  <material>
   Шелк
  </material>
  <price>
   326227
  </price>
  <rating>
   2.23
  </rating>
  <reviews>
   939797
  </reviews>
  <exclusive>
   yes
  </exclusive>
 </clothing>
 <clothing>
  <id>
   974837513
  </id>
  <name>
   Nike Pants T-5372
  </name>
  <category>
   Pants
  </category>
  <size>
   S
  </size>
  <color>
   Фиолетовый
  </color>
  <material>
   Полиэстер
  </material>
  <price>
   891237
  </price>
  <rating>
   4.11
  </rating>
  <reviews>
   162434
  </reviews>
  <exclusive>
   no
  </exclusive>
 </clothing>
 <clothing>
  <id>
   113045494
  </id>
  <name>
   Fila Shoes P-5859
  </name>
  <category>
   Shoes
  </category>
  <size>
   L
  </size>
  <color>
   Фиолетовый
  </color>
  <material>
   Хлопок
  </material>
  <price>
   364729
  </price>
  <rating>
   3.91
  </rating>
  <reviews>
   762141
  </reviews>
  <new>
   -
  </new>
  <exclusive>
   yes
  </exclusive>
  <sporty>
   yes
  </sporty>
 </clothing>
</clothing-items>
