<?xml version="1.0" encoding="utf-8"?>
<clothing-items>
 <clothing>
  <id>
   652456260
  </id>
  <name>
   Reebok Jacket R-1465
  </name>
  <category>
   Jacket
  </category>
  <size>
   XXL
  </size>
  <color>
   Красный
  </color>
  <material>
   Шелк
  </material>
  <price>
   853161
  </price>
  <rating>
   3.9
  </rating>
  <reviews>
   830309
  </reviews>
  <new>
   -
  </new>
  <sporty>
   no
  </sporty>
 </clothing>
 <clothing>
  <id>
   836245117
  </id>
  <name>
   Converse Handbags D-1142
  </name>
  <category>
   Handbags
  </category>
  <size>
   M
  </size>
  <color>
   Голубой
  </color>
  <material>
   Хлопок
  </material>
  <price>
   225541
  </price>
  <rating>
   4.09
  </rating>
  <reviews>
   626810
  </reviews>
  <new>
   +
  </new>
  <sporty>
   no
  </sporty>
 </clothing>
 <clothing>
  <id>
   140622648
  </id>
  <name>
   Lacoste Skirt P-4104
  </name>
  <category>
   Skirt
  </category>
  <size>
   XXL
  </size>
  <color>
   Оранжевый
  </color>
  <material>
   Лен
  </material>
  <price>
   560698
  </price>
  <rating>
   2.96
  </rating>
  <reviews>
   146460
  </reviews>
  <new>
   -
  </new>
  <sporty>
   yes
  </sporty>
 </clothing>
 <clothing>
  <id>
   973019548
  </id>
  <name>
   Converse Socks U-6506
  </name>
  <category>
   Socks
  </category>
  <size>
   M
  </size>
  <color>
   Оранжевый
  </color>
  <material>
   Лен
  </material>
  <price>
   388097
  </price>
  <rating>
   2.65
  </rating>
  <reviews>
   970056
  </reviews>
  <new>
   -
  </new>
  <exclusive>
   no
  </exclusive>
  <sporty>
   no
  </sporty>
 </clothing>
 <clothing>
  <id>
   171716517
  </id>
  <name>
   DC Shirt Y-2033
  </name>
  <category>
   Shirt
  </category>
  <size>
   XL
  </size>
  <color>
   Зеленый
  </color>
  <material>
   Полиэстер
  </material>
  <price>
   795962
  </price>
  <rating>
   4.21
  </rating>
  <reviews>
   828415
  </reviews>
  <exclusive>
   no
  </exclusive>
 </clothing>
 <clothing>
  <id>
   342351822
  </id>
  <name>
   Nike Shirt D-2666
  </name>
  <category>
   Shirt
  </category>
  <size>
   S
  </size>
  <color>
   Зеленый
  </color>
  <material>
   Вискоза
  </material>
  <price>
   280064
  </price>
  <rating>
   2.71
  </rating>
  <reviews>
   870111
  </reviews>
  <exclusive>
   no
  </exclusive>
  <sporty>
   no
  </sporty>
 </clothing>
 <clothing>
  <id>
   991828424
  </id>
  <name>
   Addidas Umbrellas V-7881
  </name>
  <category>
   Umbrellas
  </category>
  <size>
   XXL
  </size>
  <color>
   Синий
  </color>
  <material>
   Шелк
  </material>
  <price>
   861850
  </price>
  <rating>
   3.93
  </rating>
  <reviews>
   223694
  </reviews>
  <exclusive>
   yes
  </exclusive>
  <sporty>
   yes
  </sporty>
 </clothing>
 <clothing>
  <id>
   890038235
  </id>
  <name>
   Asics Blouse F-9410
  </name>
  <category>
   Blouse
  </category>
  <size>
   S
  </size>
  <color>
   Фиолетовый
  </color>
  <material>
   Шелк
  </material>
  <price>
   701911
  </price>
  <rating>
   3.47
  </rating>
  <reviews>
   297082
  </reviews>
  <exclusive>
   no
  </exclusive>
  <sporty>
   no
  </sporty>
 </clothing>
 <clothing>
  <id>
   592611589
  </id>
  <name>
   Fila Shoes G-2600
  </name>
  <category>
   Shoes
  </category>
  <size>
   XL
  </size>
  <color>
   Оранжевый
  </color>
  <material>
   Лен
  </material>
  <price>
   492133
  </price>
  <rating>
   1.68
  </rating>
  <reviews>
   833359
  </reviews>
  <sporty>
   no
  </sporty>
 </clothing>
 <clothing>
  <id>
   683576984
  </id>
  <name>
   Reebok Belts I-2592
  </name>
  <category>
   Belts
  </category>
  <size>
   L
  </size>
  <color>
   Синий
  </color>
  <material>
   Полиэстер
  </material>
  <price>
   601125
  </price>
  <rating>
   4.48
  </rating>
  <reviews>
   790267
  </reviews>
  <new>
   -
  </new>
  <exclusive>
   no
  </exclusive>
  <sporty>
   no
  </sporty>
 </clothing>
 <clothing>
  <id>
   909136751
  </id>
  <name>
   Under Armour Sweater I-6233
  </name>
  <category>
   Sweater
  </category>
  <size>
   XXL
  </size>
  <color>
   Красный
  </color>
  <material>
   Полиэстер
  </material>
  <price>
   224311
  </price>
  <rating>
   3.01
  </rating>
  <reviews>
   735120
  </reviews>
  <new>
   +
  </new>
  <exclusive>
   no
  </exclusive>
 </clothing>
 <clothing>
  <id>
   560142924
  </id>
  <name>
   Puma Hat V-4033
  </name>
  <category>
   Hat
  </category>
  <size>
   M
  </size>
  <color>
   Красный
  </color>
  <material>
   Шерсть
  </material>
  <price>
   431667
  </price>
  <rating>
   2.41
  </rating>
  <reviews>
   463346
  </reviews>
  <new>
   +
  </new>
  <exclusive>
   yes
  </exclusive>
  <sporty>
   no
  </sporty>
 </clothing>
 <clothing>
  <id>
   533519227
  </id>
  <name>
   DC Pants B-1125
  </name>
  <category>
   Pants
  </category>
  <size>
   L
  </size>
  <color>
   Желтый
  </color>
  <material>
   Шелк
  </material>
  <price>
   193212
  </price>
  <rating>
   3.48
  </rating>
  <reviews>
   858431
  </reviews>
  <exclusive>
   yes
  </exclusive>
  <sporty>
   yes
  </sporty>
 </clothing>
 <clothing>
  <id>
   349945337
  </id>
  <name>
   Reebok Blouse M-9138
  </name>
  <category>
   Blouse
  </category>
  <size>
   XL
  </size>
  <color>
   Красный
  </color>
  <material>
   Нейлон
  </material>
  <price>
   944355
  </price>
  <rating>
   1.73
  </rating>
  <reviews>
   661352
  </reviews>
  <new>
   +
  </new>
  <exclusive>
   no
  </exclusive>
  <sporty>
   no
  </sporty>
 </clothing>
 <clothing>
  <id>
   299514240
  </id>
  <name>
   Fila Umbrellas T-2335
  </name>
  <category>
   Umbrellas
  </category>
  <size>
   XXL
  </size>
  <color>
   Зеленый
  </color>
  <material>
   Шелк
  </material>
  <price>
   260112
  </price>
  <rating>
   1.78
  </rating>
  <reviews>
   19388
  </reviews>
 </clothing>
 <clothing>
  <id>
   117387449
  </id>
  <name>
   New Balance Jacket I-4836
  </name>
  <category>
   Jacket
  </category>
  <size>
   XL
  </size>
  <color>
   Голубой
  </color>
  <material>
   Вискоза
  </material>
  <price>
   954935
  </price>
  <rating>
   1.1
  </rating>
  <reviews>
   64257
  </reviews>
  <exclusive>
   yes
  </exclusive>
  <sporty>
   no
  </sporty>
 </clothing>
 <clothing>
  <id>
   292604234
  </id>
  <name>
   Lacoste Dress C-7940
  </name>
  <category>
   Dress
  </category>
  <size>
   S
  </size>
  <color>
   Голубой
  </color>
  <material>
   Полиэстер
  </material>
  <price>
   952997
  </price>
  <rating>
   1.37
  </rating>
  <reviews>
   793694
  </reviews>
  <new>
   -
  </new>
  <exclusive>
   no
  </exclusive>
 </clothing>
 <clothing>
  <id>
   416050338
  </id>
  <name>
   Addidas Gloves X-6292
  </name>
  <category>
   Gloves
  </category>
  <size>
   XXL
  </size>
  <color>
   Желтый
  </color>
  <material>
   Полиэстер
  </material>
  <price>
   470927
  </price>
  <rating>
   3.75
  </rating>
  <reviews>
   652000
  </reviews>
  <sporty>
   yes
  </sporty>
 </clothing>
 <clothing>
  <id>
   251913605
  </id>
  <name>
   Reebok Jacket Y-2983
  </name>
  <category>
   Jacket
  </category>
  <size>
   XXL
  </size>
  <color>
   Голубой
  </color>
  <material>
   Кожа
  </material>
  <price>
   242796
  </price>
  <rating>
   2.21
  </rating>
  <reviews>
   367661
  </reviews>
  <exclusive>
   no
  </exclusive>
 </clothing>
 <clothing>
  <id>
   673423037
  </id>
  <name>
   Fila T-shirt N-5724
  </name>
  <category>
   T-shirt
  </category>
  <size>
   M
  </size>
  <color>
   Голубой
  </color>
  <material>
   Шерсть
  </material>
  <price>
   561144
  </price>
  <rating>
   4.79
  </rating>
  <reviews>
   740225
  </reviews>
  <exclusive>
   no
  </exclusive>
 </clothing>
 <clothing>
  <id>
   714335194
  </id>
  <name>
   Converse Umbrellas P-4873
  </name>
  <category>
   Umbrellas
  </category>
  <size>
   XXL
  </size>
  <color>
   Красный
  </color>
  <material>
   Шелк
  </material>
  <price>
   274203
  </price>
  <rating>
   2.11
  </rating>
  <reviews>
   441735
  </reviews>
  <new>
   +
  </new>
 </clothing>
 <clothing>
  <id>
   325776367
  </id>
  <name>
   Asics Skirt U-2996
  </name>
  <category>
   Skirt
  </category>
  <size>
   M
  </size>
  <color>
   Желтый
  </color>
  <material>
   Лен
  </material>
  <price>
   721164
  </price>
  <rating>
   2.69
  </rating>
  <reviews>
   819651
  </reviews>
  <new>
   +
  </new>
  <exclusive>
   no
  </exclusive>
  <sporty>
   yes
  </sporty>
 </clothing>
 <clothing>
  <id>
   222426490
  </id>
  <name>
   Asics T-shirt G-5584
  </name>
  <category>
   T-shirt
  </category>
  <size>
   XXL
  </size>
  <color>
   Желтый
  </color>
  <material>
   Шелк
  </material>
  <price>
   473975
  </price>
  <rating>
   1.18
  </rating>
  <reviews>
   772478
  </reviews>
  <new>
   +
  </new>
  <exclusive>
   yes
  </exclusive>
  <sporty>
   yes
  </sporty>
 </clothing>
 <clothing>
  <id>
   652016781
  </id>
  <name>
   Nike Pants P-2322
  </name>
  <category>
   Pants
  </category>
  <size>
   L
  </size>
  <color>
   Синий
  </color>
  <material>
   Лен
  </material>
  <price>
   875125
  </price>
  <rating>
   1.56
  </rating>
  <reviews>
   430950
  </reviews>
 </clothing>
 <clothing>
  <id>
   297466374
  </id>
  <name>
   Addidas Skirt L-5722
  </name>
  <category>
   Skirt
  </category>
  <size>
   XL
  </size>
  <color>
   Фиолетовый
  </color>
  <material>
   Шерсть
  </material>
  <price>
   979821
  </price>
  <rating>
   3.12
  </rating>
  <reviews>
   936802
  </reviews>
  <new>
   -
  </new>
  <exclusive>
   no
  </exclusive>
  <sporty>
   no
  </sporty>
 </clothing>
 <clothing>
  <id>
   515721257
  </id>
  <name>
   PleinSport Pants W-2841
  </name>
  <category>
   Pants
  </category>
  <size>
   M
  </size>
  <color>
   Зеленый
  </color>
  <material>
   Шелк
  </material>
  <price>
   466435
  </price>
  <rating>
   3.07
  </rating>
  <reviews>
   892390
  </reviews>
 </clothing>
 <clothing>
  <id>
   486551196
  </id>
  <name>
   New Balance Jacket R-5847
  </name>
  <category>
   Jacket
  </category>
  <size>
   M
  </size>
  <color>
   Оранжевый
  </color>
  <material>
   Хлопок
  </material>
  <price>
   772519
  </price>
  <rating>
   1.82
  </rating>
  <reviews>
   679387
  </reviews>
  <new>
   -
  </new>
  <exclusive>
   no
  </exclusive>
  <sporty>
   yes
  </sporty>
 </clothing>
 <clothing>
  <id>
   507357299
  </id>
  <name>
   Ellesse Hat V-1609
  </name>
  <category>
   Hat
  </category>
  <size>
   L
  </size>
  <color>
   Желтый
  </color>
  <material>
   Полиэстер
  </material>
  <price>
   900871
  </price>
  <rating>
   3.02
  </rating>
  <reviews>
   635981
  </reviews>
  <new>
   -
  </new>
  <exclusive>
   no
  </exclusive>
  <sporty>
   yes
  </sporty>
 </clothing>
 <clothing>
  <id>
   327929522
  </id>
  <name>
   New Balance T-shirt N-4572
  </name>
  <category>
   T-shirt
  </category>
  <size>
   L
  </size>
  <color>
   Голубой
  </color>
  <material>
   Нейлон
  </material>
  <price>
   415303
  </price>
  <rating>
   2.29
  </rating>
  <reviews>
   830205
  </reviews>
  <exclusive>
   yes
  </exclusive>
 </clothing>
</clothing-items>
